{
  "category": "History",
  "metadata": {
    "totalQuestions": 3,
    "difficulty": {
      "easy": 1,
      "medium": 1,
      "hard": 1
    },
    "version": "1.0",
    "created": "2026-02-15",
    "updated": "2026-02-15"
  },
  "questions": [
    {
      "id": "hist_001",
      "question": "In what year did Christopher Columbus reach the Americas?",
      "answers": [
        {"text": "1492", "correct": true},
        {"text": "1482", "correct": false},
        {"text": "1502", "correct": false},
        {"text": "1492 BC (he was early)", "correct": false, "absurd": true}
      ],
      "difficulty": "easy",
      "category": "History"
    },
    {
      "id": "hist_002",
      "question": "Who was the first President of the United States?",
      "answers": [
        {"text": "George Washington", "correct": true},
        {"text": "Thomas Jefferson", "correct": false},
        {"text": "John Adams", "correct": false},
        {"text": "George Washington Carver (he invented peanuts)", "correct": false, "absurd": true}
      ],
      "difficulty": "medium",
      "category": "History"
    },
    {
      "id": "hist_003",
      "question": "The fall of the Berlin Wall occurred in which year?",
      "answers": [
        {"text": "1989", "correct": true},
        {"text": "1987", "correct": false},
        {"text": "1991", "correct": false},
        {"text": "2009 (Pink Floyd concert)", "correct": false, "absurd": true}
      ],
      "difficulty": "hard",
      "category": "History"
    }
  ]
}
